ARParser/__init__.py
ARParser/apk.py
ARParser/cli.py
ARParser/constants.py
ARParser/exceptions.py
ARParser/formatters.py
ARParser/main.py
ARParser/parser_arsc.py
ARParser/parser_axml.py
ARParser/printer.py
ARParser/stringblock.py
ARParser/helper/__init__.py
ARParser/helper/logging.py
ARParser/resources/__init__.py
ARParser/resources/public.json
ARParser/resources/public.py
ARParser/resources/public.xml
arparser-0.2.dist-info/licenses/LICENSE
arparser-0.2.dist-info/METADATA
arparser-0.2.dist-info/WHEEL
arparser-0.2.dist-info/entry_points.txt
arparser-0.2.dist-info/top_level.txt
arparser-0.2.dist-info/RECORD
