Metadata-Version: 2.4
Name: ARParser
Version: 0.2
Summary: Python library for the Android binary XML ( AXML ) file format.
Author-email: anthony <ping@42.bzh>, eighthave <hans@eds.org>, erev0s <projects@erev0s.com>, RK_TECHNO_INDIA <TechnoIndia786@gmail.com>
License:                                  Apache License
Project-URL: Homepage, https://github.com/TechnoIndian/ARParser
Project-URL: Repository, https://github.com/TechnoIndian/ARParser.git
Project-URL: Issues, https://github.com/TechnoIndian/ARParser/issues
Keywords: ARParser
Classifier: Development Status :: 5 - Production/Stable
Classifier: License :: OSI Approved :: Apache Software License
Classifier: Programming Language :: Python
Classifier: Programming Language :: Python :: 3
Classifier: Programming Language :: Python :: 3 :: Only
Classifier: Programming Language :: Python :: 3.9
Classifier: Programming Language :: Python :: 3.10
Classifier: Programming Language :: Python :: 3.11
Classifier: Programming Language :: Python :: 3.12
Classifier: Programming Language :: Python :: 3.13
Classifier: Topic :: Security
Classifier: Topic :: Software Development
Classifier: Topic :: Utilities
Requires-Python: >=3.9
License-File: LICENSE
Requires-Dist: click
Requires-Dist: pygments
Requires-Dist: rich>=14.0.0
Requires-Dist: lxml>=4.3.0
Dynamic: license-file
